{"title": "Pretty Lazy", "id": "tg-643524467607207949", "net.maunium.telegram.pack": {"short_name": "PrettyLazy", "hash": "-1632421783"}, "stickers": [{"body": "😂", "url": "mxc://griffu.xyz/WdHClfHjqtXtBpjZzfBuONZm", "info": {"w": 256, "h": 256, "size": 223349, "mimetype": "image/png", "thumbnail_url": "mxc://griffu.xyz/WdHClfHjqtXtBpjZzfBuONZm", "thumbnail_info": {"w": 256, "h": 256, "size": 223349, "mimetype": "image/png"}}, "msgtype": "m.sticker", "id": "tg-643524467607209339", "net.maunium.telegram.sticker": {"pack": {"id": "643524467607207949", "short_name": "PrettyLazy"}, "id": "643524467607209339", "emoticons": ["😂"]}}, {"body": "😘", "url": "mxc://griffu.xyz/siGRMxkGhRaeRzSMeONTqrYV", "info": {"w": 256, "h": 256, "size": 284432, "mimetype": "image/png", "thumbnail_url": "mxc://griffu.xyz/siGRMxkGhRaeRzSMeONTqrYV", "thumbnail_info": {"w": 256, "h": 256, "size": 284432, "mimetype": "image/png"}}, "msgtype": "m.sticker", "id": "tg-643524467607209304", "net.maunium.telegram.sticker": {"pack": {"id": "643524467607207949", "short_name": "PrettyLazy"}, "id": "643524467607209304", "emoticons": ["😘"]}}, {"body": "👍", "url": "mxc://griffu.xyz/hvJMcjoLQnhwuHvDIwTLXyTk", "info": {"w": 256, "h": 256, "size": 293656, "mimetype": "image/png", "thumbnail_url": "mxc://griffu.xyz/hvJMcjoLQnhwuHvDIwTLXyTk", "thumbnail_info": {"w": 256, "h": 256, "size": 293656, "mimetype": "image/png"}}, "msgtype": "m.sticker", "id": "tg-643524467607209340", "net.maunium.telegram.sticker": {"pack": {"id": "643524467607207949", "short_name": "PrettyLazy"}, "id": "643524467607209340", "emoticons": ["👍", "⏰"]}}, {"body": "😨", "url": "mxc://griffu.xyz/nPNpHZCiqVHjghkuDtArFzKn", "info": {"w": 256, "h": 256, "size": 261251, "mimetype": "image/png", "thumbnail_url": "mxc://griffu.xyz/nPNpHZCiqVHjghkuDtArFzKn", "thumbnail_info": {"w": 256, "h": 256, "size": 261251, "mimetype": "image/png"}}, "msgtype": "m.sticker", "id": "tg-643524467607209305", "net.maunium.telegram.sticker": {"pack": {"id": "643524467607207949", "short_name": "PrettyLazy"}, "id": "643524467607209305", "emoticons": ["😨", "😱"]}}, {"body": "👋", "url": "mxc://griffu.xyz/wuUWnTbaAulfSmbLnnbgKWJj", "info": {"w": 256, "h": 256, "size": 239872, "mimetype": "image/png", "thumbnail_url": "mxc://griffu.xyz/wuUWnTbaAulfSmbLnnbgKWJj", "thumbnail_info": {"w": 256, "h": 256, "size": 239872, "mimetype": "image/png"}}, "msgtype": "m.sticker", "id": "tg-643524467607209307", "net.maunium.telegram.sticker": {"pack": {"id": "643524467607207949", "short_name": "PrettyLazy"}, "id": "643524467607209307", "emoticons": ["👋", "🙂"]}}, {"body": "📚", "url": "mxc://griffu.xyz/wozgGPnqiYPJjMSRuLqEBPqE", "info": {"w": 256, "h": 256, "size": 306168, "mimetype": "image/png", "thumbnail_url": "mxc://griffu.xyz/wozgGPnqiYPJjMSRuLqEBPqE", "thumbnail_info": {"w": 256, "h": 256, "size": 306168, "mimetype": "image/png"}}, "msgtype": "m.sticker", "id": "tg-643524467607209308", "net.maunium.telegram.sticker": {"pack": {"id": "643524467607207949", "short_name": "PrettyLazy"}, "id": "643524467607209308", "emoticons": ["📚"]}}, {"body": "🤷", "url": "mxc://griffu.xyz/QjhTaGvZPuimTsTdYvScNXVU", "info": {"w": 256, "h": 256, "size": 277684, "mimetype": "image/png", "thumbnail_url": "mxc://griffu.xyz/QjhTaGvZPuimTsTdYvScNXVU", "thumbnail_info": {"w": 256, "h": 256, "size": 277684, "mimetype": "image/png"}}, "msgtype": "m.sticker", "id": "tg-643524467607209341", "net.maunium.telegram.sticker": {"pack": {"id": "643524467607207949", "short_name": "PrettyLazy"}, "id": "643524467607209341", "emoticons": ["🤷"]}}, {"body": "🤗", "url": "mxc://griffu.xyz/xsqHQCTLcnsyEyLXikEpRxkm", "info": {"w": 256, "h": 256, "size": 290443, "mimetype": "image/png", "thumbnail_url": "mxc://griffu.xyz/xsqHQCTLcnsyEyLXikEpRxkm", "thumbnail_info": {"w": 256, "h": 256, "size": 290443, "mimetype": "image/png"}}, "msgtype": "m.sticker", "id": "tg-643524467607209309", "net.maunium.telegram.sticker": {"pack": {"id": "643524467607207949", "short_name": "PrettyLazy"}, "id": "643524467607209309", "emoticons": ["🤗", "🛌"]}}, {"body": "😍", "url": "mxc://griffu.xyz/iCUcIwYowxwFtYUeJUPfFPqD", "info": {"w": 256, "h": 256, "size": 322528, "mimetype": "image/png", "thumbnail_url": "mxc://griffu.xyz/iCUcIwYowxwFtYUeJUPfFPqD", "thumbnail_info": {"w": 256, "h": 256, "size": 322528, "mimetype": "image/png"}}, "msgtype": "m.sticker", "id": "tg-643524467607209311", "net.maunium.telegram.sticker": {"pack": {"id": "643524467607207949", "short_name": "PrettyLazy"}, "id": "643524467607209311", "emoticons": ["😍", "💙"]}}, {"body": "☕", "url": "mxc://griffu.xyz/BMeiFcbOLFDeUeNuSsqTDQIg", "info": {"w": 256, "h": 256, "size": 296266, "mimetype": "image/png", "thumbnail_url": "mxc://griffu.xyz/BMeiFcbOLFDeUeNuSsqTDQIg", "thumbnail_info": {"w": 256, "h": 256, "size": 296266, "mimetype": "image/png"}}, "msgtype": "m.sticker", "id": "tg-643524467607209342", "net.maunium.telegram.sticker": {"pack": {"id": "643524467607207949", "short_name": "PrettyLazy"}, "id": "643524467607209342", "emoticons": ["☕"]}}, {"body": "🤡", "url": "mxc://griffu.xyz/mKmkoQOWChNTvJZksJRkjwSX", "info": {"w": 256, "h": 256, "size": 381568, "mimetype": "image/png", "thumbnail_url": "mxc://griffu.xyz/mKmkoQOWChNTvJZksJRkjwSX", "thumbnail_info": {"w": 256, "h": 256, "size": 381568, "mimetype": "image/png"}}, "msgtype": "m.sticker", "id": "tg-643524467607209312", "net.maunium.telegram.sticker": {"pack": {"id": "643524467607207949", "short_name": "PrettyLazy"}, "id": "643524467607209312", "emoticons": ["🤡"]}}, {"body": "😐", "url": "mxc://griffu.xyz/AGrXPqmhHNXVQslQGjQPfbjO", "info": {"w": 256, "h": 256, "size": 233471, "mimetype": "image/png", "thumbnail_url": "mxc://griffu.xyz/AGrXPqmhHNXVQslQGjQPfbjO", "thumbnail_info": {"w": 256, "h": 256, "size": 233471, "mimetype": "image/png"}}, "msgtype": "m.sticker", "id": "tg-643524467607209344", "net.maunium.telegram.sticker": {"pack": {"id": "643524467607207949", "short_name": "PrettyLazy"}, "id": "643524467607209344", "emoticons": ["😐", "💻"]}}, {"body": "🤦", "url": "mxc://griffu.xyz/uqIfKdKJGggXlvStzKYhejaF", "info": {"w": 256, "h": 256, "size": 208233, "mimetype": "image/png", "thumbnail_url": "mxc://griffu.xyz/uqIfKdKJGggXlvStzKYhejaF", "thumbnail_info": {"w": 256, "h": 256, "size": 208233, "mimetype": "image/png"}}, "msgtype": "m.sticker", "id": "tg-643524467607209314", "net.maunium.telegram.sticker": {"pack": {"id": "643524467607207949", "short_name": "PrettyLazy"}, "id": "643524467607209314", "emoticons": ["🤦"]}}, {"body": "😳", "url": "mxc://griffu.xyz/IpEQTjfUXHTrHVakJYsvbKyJ", "info": {"w": 256, "h": 256, "size": 231859, "mimetype": "image/png", "thumbnail_url": "mxc://griffu.xyz/IpEQTjfUXHTrHVakJYsvbKyJ", "thumbnail_info": {"w": 256, "h": 256, "size": 231859, "mimetype": "image/png"}}, "msgtype": "m.sticker", "id": "tg-643524467607209315", "net.maunium.telegram.sticker": {"pack": {"id": "643524467607207949", "short_name": "PrettyLazy"}, "id": "643524467607209315", "emoticons": ["😳"]}}, {"body": "😴", "url": "mxc://griffu.xyz/eEjsOJhUhMSSkSBdIrulsfYw", "info": {"w": 256, "h": 256, "size": 288460, "mimetype": "image/png", "thumbnail_url": "mxc://griffu.xyz/eEjsOJhUhMSSkSBdIrulsfYw", "thumbnail_info": {"w": 256, "h": 256, "size": 288460, "mimetype": "image/png"}}, "msgtype": "m.sticker", "id": "tg-643524467607209316", "net.maunium.telegram.sticker": {"pack": {"id": "643524467607207949", "short_name": "PrettyLazy"}, "id": "643524467607209316", "emoticons": ["😴", "⌨"]}}, {"body": "😕", "url": "mxc://griffu.xyz/DBYIykkrCeUpdheyPwGhfhcR", "info": {"w": 256, "h": 256, "size": 278479, "mimetype": "image/png", "thumbnail_url": "mxc://griffu.xyz/DBYIykkrCeUpdheyPwGhfhcR", "thumbnail_info": {"w": 256, "h": 256, "size": 278479, "mimetype": "image/png"}}, "msgtype": "m.sticker", "id": "tg-643524467607209348", "net.maunium.telegram.sticker": {"pack": {"id": "643524467607207949", "short_name": "PrettyLazy"}, "id": "643524467607209348", "emoticons": ["😕"]}}, {"body": "🤴", "url": "mxc://griffu.xyz/DSXMWdJrBbZUHeGtkuDolrpm", "info": {"w": 256, "h": 256, "size": 321383, "mimetype": "image/png", "thumbnail_url": "mxc://griffu.xyz/DSXMWdJrBbZUHeGtkuDolrpm", "thumbnail_info": {"w": 256, "h": 256, "size": 321383, "mimetype": "image/png"}}, "msgtype": "m.sticker", "id": "tg-643524467607209317", "net.maunium.telegram.sticker": {"pack": {"id": "643524467607207949", "short_name": "PrettyLazy"}, "id": "643524467607209317", "emoticons": ["🤴"]}}, {"body": "😠", "url": "mxc://griffu.xyz/FZGnyUdZYOOwpeldpoaTRJeU", "info": {"w": 256, "h": 256, "size": 314560, "mimetype": "image/png", "thumbnail_url": "mxc://griffu.xyz/FZGnyUdZYOOwpeldpoaTRJeU", "thumbnail_info": {"w": 256, "h": 256, "size": 314560, "mimetype": "image/png"}}, "msgtype": "m.sticker", "id": "tg-643524467607209318", "net.maunium.telegram.sticker": {"pack": {"id": "643524467607207949", "short_name": "PrettyLazy"}, "id": "643524467607209318", "emoticons": ["😠", "🔥"]}}, {"body": "😦", "url": "mxc://griffu.xyz/wUYBsdbsWOisFVLcbYcCnKkf", "info": {"w": 256, "h": 256, "size": 263269, "mimetype": "image/png", "thumbnail_url": "mxc://griffu.xyz/wUYBsdbsWOisFVLcbYcCnKkf", "thumbnail_info": {"w": 256, "h": 256, "size": 263269, "mimetype": "image/png"}}, "msgtype": "m.sticker", "id": "tg-643524467607209343", "net.maunium.telegram.sticker": {"pack": {"id": "643524467607207949", "short_name": "PrettyLazy"}, "id": "643524467607209343", "emoticons": ["😦"]}}, {"body": "💵", "url": "mxc://griffu.xyz/YAXTPFaXvFmiSSCgLWMZWSzV", "info": {"w": 256, "h": 256, "size": 296117, "mimetype": "image/png", "thumbnail_url": "mxc://griffu.xyz/YAXTPFaXvFmiSSCgLWMZWSzV", "thumbnail_info": {"w": 256, "h": 256, "size": 296117, "mimetype": "image/png"}}, "msgtype": "m.sticker", "id": "tg-643524467607209321", "net.maunium.telegram.sticker": {"pack": {"id": "643524467607207949", "short_name": "PrettyLazy"}, "id": "643524467607209321", "emoticons": ["💵", "💸"]}}, {"body": "🕰", "url": "mxc://griffu.xyz/weytEoypcVzLDyzQMlYkYzAr", "info": {"w": 256, "h": 256, "size": 272595, "mimetype": "image/png", "thumbnail_url": "mxc://griffu.xyz/weytEoypcVzLDyzQMlYkYzAr", "thumbnail_info": {"w": 256, "h": 256, "size": 272595, "mimetype": "image/png"}}, "msgtype": "m.sticker", "id": "tg-643524467607209322", "net.maunium.telegram.sticker": {"pack": {"id": "643524467607207949", "short_name": "PrettyLazy"}, "id": "643524467607209322", "emoticons": ["🕰", "🕧"]}}, {"body": "🙃", "url": "mxc://griffu.xyz/hPEHdsQbFfTjSiTgpwPxKoJH", "info": {"w": 256, "h": 256, "size": 321498, "mimetype": "image/png", "thumbnail_url": "mxc://griffu.xyz/hPEHdsQbFfTjSiTgpwPxKoJH", "thumbnail_info": {"w": 256, "h": 256, "size": 321498, "mimetype": "image/png"}}, "msgtype": "m.sticker", "id": "tg-643524467607209323", "net.maunium.telegram.sticker": {"pack": {"id": "643524467607207949", "short_name": "PrettyLazy"}, "id": "643524467607209323", "emoticons": ["🙃", "😒"]}}, {"body": "😌", "url": "mxc://griffu.xyz/VaIWUwqtcpUYJbSCgrzdCuGK", "info": {"w": 256, "h": 256, "size": 316666, "mimetype": "image/png", "thumbnail_url": "mxc://griffu.xyz/VaIWUwqtcpUYJbSCgrzdCuGK", "thumbnail_info": {"w": 256, "h": 256, "size": 316666, "mimetype": "image/png"}}, "msgtype": "m.sticker", "id": "tg-643524467607209324", "net.maunium.telegram.sticker": {"pack": {"id": "643524467607207949", "short_name": "PrettyLazy"}, "id": "643524467607209324", "emoticons": ["😌"]}}, {"body": "✨", "url": "mxc://griffu.xyz/DVMfkmDBCHbShfBhIWTwnPsk", "info": {"w": 256, "h": 256, "size": 298365, "mimetype": "image/png", "thumbnail_url": "mxc://griffu.xyz/DVMfkmDBCHbShfBhIWTwnPsk", "thumbnail_info": {"w": 256, "h": 256, "size": 298365, "mimetype": "image/png"}}, "msgtype": "m.sticker", "id": "tg-643524467607209325", "net.maunium.telegram.sticker": {"pack": {"id": "643524467607207949", "short_name": "PrettyLazy"}, "id": "643524467607209325", "emoticons": ["✨"]}}, {"body": "🛁", "url": "mxc://griffu.xyz/vhGsuxnTulIaTlBKlHaimWeC", "info": {"w": 256, "h": 256, "size": 302225, "mimetype": "image/png", "thumbnail_url": "mxc://griffu.xyz/vhGsuxnTulIaTlBKlHaimWeC", "thumbnail_info": {"w": 256, "h": 256, "size": 302225, "mimetype": "image/png"}}, "msgtype": "m.sticker", "id": "tg-643524467607209326", "net.maunium.telegram.sticker": {"pack": {"id": "643524467607207949", "short_name": "PrettyLazy"}, "id": "643524467607209326", "emoticons": ["🛁", "🛀"]}}, {"body": "💐", "url": "mxc://griffu.xyz/jaEMCCKlfidculzFMLuaVxXh", "info": {"w": 256, "h": 256, "size": 332821, "mimetype": "image/png", "thumbnail_url": "mxc://griffu.xyz/jaEMCCKlfidculzFMLuaVxXh", "thumbnail_info": {"w": 256, "h": 256, "size": 332821, "mimetype": "image/png"}}, "msgtype": "m.sticker", "id": "tg-643524467607209330", "net.maunium.telegram.sticker": {"pack": {"id": "643524467607207949", "short_name": "PrettyLazy"}, "id": "643524467607209330", "emoticons": ["💐"]}}, {"body": "😬", "url": "mxc://griffu.xyz/SkkrSgVIDKTQeAYJjdAZfhSj", "info": {"w": 256, "h": 256, "size": 255647, "mimetype": "image/png", "thumbnail_url": "mxc://griffu.xyz/SkkrSgVIDKTQeAYJjdAZfhSj", "thumbnail_info": {"w": 256, "h": 256, "size": 255647, "mimetype": "image/png"}}, "msgtype": "m.sticker", "id": "tg-643524467607209331", "net.maunium.telegram.sticker": {"pack": {"id": "643524467607207949", "short_name": "PrettyLazy"}, "id": "643524467607209331", "emoticons": ["😬"]}}, {"body": "🎂", "url": "mxc://griffu.xyz/QBXIZnWMPzZimrphJmWTDvzI", "info": {"w": 256, "h": 256, "size": 362033, "mimetype": "image/png", "thumbnail_url": "mxc://griffu.xyz/QBXIZnWMPzZimrphJmWTDvzI", "thumbnail_info": {"w": 256, "h": 256, "size": 362033, "mimetype": "image/png"}}, "msgtype": "m.sticker", "id": "tg-643524467607209332", "net.maunium.telegram.sticker": {"pack": {"id": "643524467607207949", "short_name": "PrettyLazy"}, "id": "643524467607209332", "emoticons": ["🎂", "🎉"]}}, {"body": "🤔", "url": "mxc://griffu.xyz/IDVYECGdNeOMFGqMfaVJdkeU", "info": {"w": 256, "h": 256, "size": 214247, "mimetype": "image/png", "thumbnail_url": "mxc://griffu.xyz/IDVYECGdNeOMFGqMfaVJdkeU", "thumbnail_info": {"w": 256, "h": 256, "size": 214247, "mimetype": "image/png"}}, "msgtype": "m.sticker", "id": "tg-643524467607209333", "net.maunium.telegram.sticker": {"pack": {"id": "643524467607207949", "short_name": "PrettyLazy"}, "id": "643524467607209333", "emoticons": ["🤔"]}}, {"body": "🤙", "url": "mxc://griffu.xyz/BgPHMhXBoZlUGXedYyFtNOwd", "info": {"w": 256, "h": 256, "size": 249018, "mimetype": "image/png", "thumbnail_url": "mxc://griffu.xyz/BgPHMhXBoZlUGXedYyFtNOwd", "thumbnail_info": {"w": 256, "h": 256, "size": 249018, "mimetype": "image/png"}}, "msgtype": "m.sticker", "id": "tg-643524467607209334", "net.maunium.telegram.sticker": {"pack": {"id": "643524467607207949", "short_name": "PrettyLazy"}, "id": "643524467607209334", "emoticons": ["🤙", "😏"]}}, {"body": "🤢", "url": "mxc://griffu.xyz/IZatTOBvutvOoRzwXvkGCwDU", "info": {"w": 256, "h": 256, "size": 247788, "mimetype": "image/png", "thumbnail_url": "mxc://griffu.xyz/IZatTOBvutvOoRzwXvkGCwDU", "thumbnail_info": {"w": 256, "h": 256, "size": 247788, "mimetype": "image/png"}}, "msgtype": "m.sticker", "id": "tg-643524467607209335", "net.maunium.telegram.sticker": {"pack": {"id": "643524467607207949", "short_name": "PrettyLazy"}, "id": "643524467607209335", "emoticons": ["🤢"]}}, {"body": "😢", "url": "mxc://griffu.xyz/jbiDJdsQTYQoKGKueQtzDaJk", "info": {"w": 256, "h": 256, "size": 188752, "mimetype": "image/png", "thumbnail_url": "mxc://griffu.xyz/jbiDJdsQTYQoKGKueQtzDaJk", "thumbnail_info": {"w": 256, "h": 256, "size": 188752, "mimetype": "image/png"}}, "msgtype": "m.sticker", "id": "tg-643524467607209337", "net.maunium.telegram.sticker": {"pack": {"id": "643524467607207949", "short_name": "PrettyLazy"}, "id": "643524467607209337", "emoticons": ["😢"]}}, {"body": "🏃", "url": "mxc://griffu.xyz/kdBIsioYvOLCBUdQOPdZacJz", "info": {"w": 256, "h": 256, "size": 311526, "mimetype": "image/png", "thumbnail_url": "mxc://griffu.xyz/kdBIsioYvOLCBUdQOPdZacJz", "thumbnail_info": {"w": 256, "h": 256, "size": 311526, "mimetype": "image/png"}}, "msgtype": "m.sticker", "id": "tg-643524467607209338", "net.maunium.telegram.sticker": {"pack": {"id": "643524467607207949", "short_name": "PrettyLazy"}, "id": "643524467607209338", "emoticons": ["🏃"]}}, {"body": "🤠", "url": "mxc://griffu.xyz/pSdsTxRzkYdmWZExropowaQu", "info": {"w": 256, "h": 256, "size": 332845, "mimetype": "image/png", "thumbnail_url": "mxc://griffu.xyz/pSdsTxRzkYdmWZExropowaQu", "thumbnail_info": {"w": 256, "h": 256, "size": 332845, "mimetype": "image/png"}}, "msgtype": "m.sticker", "id": "tg-643524467607209347", "net.maunium.telegram.sticker": {"pack": {"id": "643524467607207949", "short_name": "PrettyLazy"}, "id": "643524467607209347", "emoticons": ["🤠"]}}, {"body": "🍝", "url": "mxc://griffu.xyz/nMYQHvBemMaIdzYkXoAlZBjP", "info": {"w": 256, "h": 256, "size": 268968, "mimetype": "image/png", "thumbnail_url": "mxc://griffu.xyz/nMYQHvBemMaIdzYkXoAlZBjP", "thumbnail_info": {"w": 256, "h": 256, "size": 268968, "mimetype": "image/png"}}, "msgtype": "m.sticker", "id": "tg-643524467607209349", "net.maunium.telegram.sticker": {"pack": {"id": "643524467607207949", "short_name": "PrettyLazy"}, "id": "643524467607209349", "emoticons": ["🍝", "📺"]}}]}